file_structure_builder/__init__.py
file_structure_builder/builder.py
file_structure_builder/cli.py
file_structure_builder/parser.py
file_structure_builder/utils.py
file_structure_builder-1.0.2.dist-info/METADATA
file_structure_builder-1.0.2.dist-info/WHEEL
file_structure_builder-1.0.2.dist-info/entry_points.txt
file_structure_builder-1.0.2.dist-info/top_level.txt
file_structure_builder-1.0.2.dist-info/RECORD
